<?xml version="1.0" encoding="UTF-8"?>
<!DOCTYPE mapper PUBLIC "-//mybatis.org//DTD Mapper 3.0//EN" "http://mybatis.org/dtd/mybatis-3-mapper.dtd">
<mapper namespace="com.nagisazz.base.dao.base.ZlpUserMapper">
  <resultMap id="BaseResultMap" type="com.nagisazz.base.entity.ZlpUser">
    <!--
      WARNING - @mbg.generated
      This element is automatically generated by MyBatis Generator, do not modify.
      This element was generated on Fri Dec 09 18:24:42 CST 2022.
    -->
    <id column="n_id" jdbcType="BIGINT" property="id" />
    <result column="c_loginid" jdbcType="VARCHAR" property="loginid" />
    <result column="c_name" jdbcType="VARCHAR" property="name" />
    <result column="c_password" jdbcType="VARCHAR" property="password" />
    <result column="c_phone" jdbcType="VARCHAR" property="phone" />
    <result column="c_mail" jdbcType="VARCHAR" property="mail" />
    <result column="c_avatarurl" jdbcType="VARCHAR" property="avatarurl" />
    <result column="c_register_system" jdbcType="VARCHAR" property="registerSystem" />
    <result column="c_last_ip" jdbcType="VARCHAR" property="lastIp" />
    <result column="c_last_system" jdbcType="VARCHAR" property="lastSystem" />
    <result column="n_login_number" jdbcType="INTEGER" property="loginNumber" />
    <result column="c_ext" jdbcType="VARCHAR" property="ext" />
    <result column="n_valid" jdbcType="INTEGER" property="valid" />
    <result column="dt_create_time" jdbcType="TIMESTAMP" property="createTime" />
    <result column="dt_update_time" jdbcType="TIMESTAMP" property="updateTime" />
    <result column="dt_last_login_time" jdbcType="TIMESTAMP" property="lastLoginTime" />
  </resultMap>
  <sql id="Base_Column_List">
    <!--
      WARNING - @mbg.generated
      This element is automatically generated by MyBatis Generator, do not modify.
      This element was generated on Fri Dec 09 18:24:42 CST 2022.
    -->
    n_id, c_loginid, c_name, c_password, c_phone, c_mail, c_avatarurl, c_register_system, 
    c_last_ip, c_last_system, n_login_number, c_ext, n_valid, dt_create_time, dt_update_time, 
    dt_last_login_time
  </sql>
  <select id="selectByPrimaryKey" parameterType="java.lang.Long" resultMap="BaseResultMap">
    <!--
      WARNING - @mbg.generated
      This element is automatically generated by MyBatis Generator, do not modify.
      This element was generated on Fri Dec 09 18:24:42 CST 2022.
    -->
    select 
    <include refid="Base_Column_List" />
    from t_zlp_user
    where n_id = #{id,jdbcType=BIGINT}
  </select>
  <delete id="deleteByPrimaryKey" parameterType="java.lang.Long">
    <!--
      WARNING - @mbg.generated
      This element is automatically generated by MyBatis Generator, do not modify.
      This element was generated on Fri Dec 09 18:24:42 CST 2022.
    -->
    delete from t_zlp_user
    where n_id = #{id,jdbcType=BIGINT}
  </delete>
  <insert id="insert" parameterType="com.nagisazz.base.entity.ZlpUser">
    <!--
      WARNING - @mbg.generated
      This element is automatically generated by MyBatis Generator, do not modify.
      This element was generated on Fri Dec 09 18:24:42 CST 2022.
    -->
    insert into t_zlp_user (n_id, c_loginid, c_name, 
      c_password, c_phone, c_mail, 
      c_avatarurl, c_register_system, c_last_ip, 
      c_last_system, n_login_number, c_ext, 
      n_valid, dt_create_time, dt_update_time, 
      dt_last_login_time)
    values (#{id,jdbcType=BIGINT}, #{loginid,jdbcType=VARCHAR}, #{name,jdbcType=VARCHAR}, 
      #{password,jdbcType=VARCHAR}, #{phone,jdbcType=VARCHAR}, #{mail,jdbcType=VARCHAR}, 
      #{avatarurl,jdbcType=VARCHAR}, #{registerSystem,jdbcType=VARCHAR}, #{lastIp,jdbcType=VARCHAR}, 
      #{lastSystem,jdbcType=VARCHAR}, #{loginNumber,jdbcType=INTEGER}, #{ext,jdbcType=VARCHAR}, 
      #{valid,jdbcType=INTEGER}, #{createTime,jdbcType=TIMESTAMP}, #{updateTime,jdbcType=TIMESTAMP}, 
      #{lastLoginTime,jdbcType=TIMESTAMP})
  </insert>
  <insert id="insertSelective" parameterType="com.nagisazz.base.entity.ZlpUser">
    <!--
      WARNING - @mbg.generated
      This element is automatically generated by MyBatis Generator, do not modify.
      This element was generated on Fri Dec 09 18:24:42 CST 2022.
    -->
    insert into t_zlp_user
    <trim prefix="(" suffix=")" suffixOverrides=",">
      <if test="id != null">
        n_id,
      </if>
      <if test="loginid != null">
        c_loginid,
      </if>
      <if test="name != null">
        c_name,
      </if>
      <if test="password != null">
        c_password,
      </if>
      <if test="phone != null">
        c_phone,
      </if>
      <if test="mail != null">
        c_mail,
      </if>
      <if test="avatarurl != null">
        c_avatarurl,
      </if>
      <if test="registerSystem != null">
        c_register_system,
      </if>
      <if test="lastIp != null">
        c_last_ip,
      </if>
      <if test="lastSystem != null">
        c_last_system,
      </if>
      <if test="loginNumber != null">
        n_login_number,
      </if>
      <if test="ext != null">
        c_ext,
      </if>
      <if test="valid != null">
        n_valid,
      </if>
      <if test="createTime != null">
        dt_create_time,
      </if>
      <if test="updateTime != null">
        dt_update_time,
      </if>
      <if test="lastLoginTime != null">
        dt_last_login_time,
      </if>
    </trim>
    <trim prefix="values (" suffix=")" suffixOverrides=",">
      <if test="id != null">
        #{id,jdbcType=BIGINT},
      </if>
      <if test="loginid != null">
        #{loginid,jdbcType=VARCHAR},
      </if>
      <if test="name != null">
        #{name,jdbcType=VARCHAR},
      </if>
      <if test="password != null">
        #{password,jdbcType=VARCHAR},
      </if>
      <if test="phone != null">
        #{phone,jdbcType=VARCHAR},
      </if>
      <if test="mail != null">
        #{mail,jdbcType=VARCHAR},
      </if>
      <if test="avatarurl != null">
        #{avatarurl,jdbcType=VARCHAR},
      </if>
      <if test="registerSystem != null">
        #{registerSystem,jdbcType=VARCHAR},
      </if>
      <if test="lastIp != null">
        #{lastIp,jdbcType=VARCHAR},
      </if>
      <if test="lastSystem != null">
        #{lastSystem,jdbcType=VARCHAR},
      </if>
      <if test="loginNumber != null">
        #{loginNumber,jdbcType=INTEGER},
      </if>
      <if test="ext != null">
        #{ext,jdbcType=VARCHAR},
      </if>
      <if test="valid != null">
        #{valid,jdbcType=INTEGER},
      </if>
      <if test="createTime != null">
        #{createTime,jdbcType=TIMESTAMP},
      </if>
      <if test="updateTime != null">
        #{updateTime,jdbcType=TIMESTAMP},
      </if>
      <if test="lastLoginTime != null">
        #{lastLoginTime,jdbcType=TIMESTAMP},
      </if>
    </trim>
  </insert>
  <update id="updateByPrimaryKeySelective" parameterType="com.nagisazz.base.entity.ZlpUser">
    <!--
      WARNING - @mbg.generated
      This element is automatically generated by MyBatis Generator, do not modify.
      This element was generated on Fri Dec 09 18:24:42 CST 2022.
    -->
    update t_zlp_user
    <set>
      <if test="loginid != null">
        c_loginid = #{loginid,jdbcType=VARCHAR},
      </if>
      <if test="name != null">
        c_name = #{name,jdbcType=VARCHAR},
      </if>
      <if test="password != null">
        c_password = #{password,jdbcType=VARCHAR},
      </if>
      <if test="phone != null">
        c_phone = #{phone,jdbcType=VARCHAR},
      </if>
      <if test="mail != null">
        c_mail = #{mail,jdbcType=VARCHAR},
      </if>
      <if test="avatarurl != null">
        c_avatarurl = #{avatarurl,jdbcType=VARCHAR},
      </if>
      <if test="registerSystem != null">
        c_register_system = #{registerSystem,jdbcType=VARCHAR},
      </if>
      <if test="lastIp != null">
        c_last_ip = #{lastIp,jdbcType=VARCHAR},
      </if>
      <if test="lastSystem != null">
        c_last_system = #{lastSystem,jdbcType=VARCHAR},
      </if>
      <if test="loginNumber != null">
        n_login_number = #{loginNumber,jdbcType=INTEGER},
      </if>
      <if test="ext != null">
        c_ext = #{ext,jdbcType=VARCHAR},
      </if>
      <if test="valid != null">
        n_valid = #{valid,jdbcType=INTEGER},
      </if>
      <if test="createTime != null">
        dt_create_time = #{createTime,jdbcType=TIMESTAMP},
      </if>
      <if test="updateTime != null">
        dt_update_time = #{updateTime,jdbcType=TIMESTAMP},
      </if>
      <if test="lastLoginTime != null">
        dt_last_login_time = #{lastLoginTime,jdbcType=TIMESTAMP},
      </if>
    </set>
    where n_id = #{id,jdbcType=BIGINT}
  </update>
  <update id="updateByPrimaryKey" parameterType="com.nagisazz.base.entity.ZlpUser">
    <!--
      WARNING - @mbg.generated
      This element is automatically generated by MyBatis Generator, do not modify.
      This element was generated on Fri Dec 09 18:24:42 CST 2022.
    -->
    update t_zlp_user
    set c_loginid = #{loginid,jdbcType=VARCHAR},
      c_name = #{name,jdbcType=VARCHAR},
      c_password = #{password,jdbcType=VARCHAR},
      c_phone = #{phone,jdbcType=VARCHAR},
      c_mail = #{mail,jdbcType=VARCHAR},
      c_avatarurl = #{avatarurl,jdbcType=VARCHAR},
      c_register_system = #{registerSystem,jdbcType=VARCHAR},
      c_last_ip = #{lastIp,jdbcType=VARCHAR},
      c_last_system = #{lastSystem,jdbcType=VARCHAR},
      n_login_number = #{loginNumber,jdbcType=INTEGER},
      c_ext = #{ext,jdbcType=VARCHAR},
      n_valid = #{valid,jdbcType=INTEGER},
      dt_create_time = #{createTime,jdbcType=TIMESTAMP},
      dt_update_time = #{updateTime,jdbcType=TIMESTAMP},
      dt_last_login_time = #{lastLoginTime,jdbcType=TIMESTAMP}
    where n_id = #{id,jdbcType=BIGINT}
  </update>
  <sql id="BASE_QUERY">
    <trim prefix="WHERE" prefixOverrides="AND|OR">
      <if test="null != id">
         and n_id = #{id,jdbcType=BIGINT}
      </if>
      <if test="null != loginid">
         and c_loginid = #{loginid,jdbcType=VARCHAR}
      </if>
      <if test="null != name">
         and c_name = #{name,jdbcType=VARCHAR}
      </if>
      <if test="null != password">
         and c_password = #{password,jdbcType=VARCHAR}
      </if>
      <if test="null != phone">
         and c_phone = #{phone,jdbcType=VARCHAR}
      </if>
      <if test="null != mail">
         and c_mail = #{mail,jdbcType=VARCHAR}
      </if>
      <if test="null != avatarurl">
         and c_avatarurl = #{avatarurl,jdbcType=VARCHAR}
      </if>
      <if test="null != registerSystem">
         and c_register_system = #{registerSystem,jdbcType=VARCHAR}
      </if>
      <if test="null != lastIp">
         and c_last_ip = #{lastIp,jdbcType=VARCHAR}
      </if>
      <if test="null != lastSystem">
         and c_last_system = #{lastSystem,jdbcType=VARCHAR}
      </if>
      <if test="null != loginNumber">
         and n_login_number = #{loginNumber,jdbcType=INTEGER}
      </if>
      <if test="null != ext">
         and c_ext = #{ext,jdbcType=VARCHAR}
      </if>
      <if test="null != valid">
         and n_valid = #{valid,jdbcType=INTEGER}
      </if>
      <if test="null != createTime">
         and dt_create_time = #{createTime,jdbcType=TIMESTAMP}
      </if>
      <if test="null != updateTime">
         and dt_update_time = #{updateTime,jdbcType=TIMESTAMP}
      </if>
      <if test="null != lastLoginTime">
         and dt_last_login_time = #{lastLoginTime,jdbcType=TIMESTAMP}
      </if>
    </trim>
  </sql>
  <select id="selectOne" parameterType="com.nagisazz.base.entity.ZlpUser" resultMap="BaseResultMap">
    select 
    <include refid="Base_Column_List" />
    from t_zlp_user
    <include refid="BASE_QUERY" />
    limit 1
  </select>
  <select id="selectList" parameterType="com.nagisazz.base.entity.ZlpUser" resultMap="BaseResultMap">
    select 
    <include refid="Base_Column_List" />
    from t_zlp_user
    <include refid="BASE_QUERY" />
  </select>
  <update id="batchUpdate" parameterType="java.util.List">
    <foreach collection="list" item="item" separator=";">
      update t_zlp_user
      <set>
        c_loginid = #{item.loginid,jdbcType=VARCHAR},
        c_name = #{item.name,jdbcType=VARCHAR},
        c_password = #{item.password,jdbcType=VARCHAR},
        c_phone = #{item.phone,jdbcType=VARCHAR},
        c_mail = #{item.mail,jdbcType=VARCHAR},
        c_avatarurl = #{item.avatarurl,jdbcType=VARCHAR},
        c_register_system = #{item.registerSystem,jdbcType=VARCHAR},
        c_last_ip = #{item.lastIp,jdbcType=VARCHAR},
        c_last_system = #{item.lastSystem,jdbcType=VARCHAR},
        n_login_number = #{item.loginNumber,jdbcType=INTEGER},
        c_ext = #{item.ext,jdbcType=VARCHAR},
        n_valid = #{item.valid,jdbcType=INTEGER},
        dt_create_time = #{item.createTime,jdbcType=TIMESTAMP},
        dt_update_time = #{item.updateTime,jdbcType=TIMESTAMP},
        dt_last_login_time = #{item.lastLoginTime,jdbcType=TIMESTAMP}
      </set>
      where n_id = #{item.id,jdbcType=BIGINT}
    </foreach>
  </update>
  <update id="batchUpdateSelective" parameterType="java.util.List">
    <foreach collection="list" item="item" separator=";">
      update t_zlp_user
      <set>
        <if test="item.loginid != null">
          c_loginid = #{item.loginid,jdbcType=VARCHAR},
        </if>
        <if test="item.name != null">
          c_name = #{item.name,jdbcType=VARCHAR},
        </if>
        <if test="item.password != null">
          c_password = #{item.password,jdbcType=VARCHAR},
        </if>
        <if test="item.phone != null">
          c_phone = #{item.phone,jdbcType=VARCHAR},
        </if>
        <if test="item.mail != null">
          c_mail = #{item.mail,jdbcType=VARCHAR},
        </if>
        <if test="item.avatarurl != null">
          c_avatarurl = #{item.avatarurl,jdbcType=VARCHAR},
        </if>
        <if test="item.registerSystem != null">
          c_register_system = #{item.registerSystem,jdbcType=VARCHAR},
        </if>
        <if test="item.lastIp != null">
          c_last_ip = #{item.lastIp,jdbcType=VARCHAR},
        </if>
        <if test="item.lastSystem != null">
          c_last_system = #{item.lastSystem,jdbcType=VARCHAR},
        </if>
        <if test="item.loginNumber != null">
          n_login_number = #{item.loginNumber,jdbcType=INTEGER},
        </if>
        <if test="item.ext != null">
          c_ext = #{item.ext,jdbcType=VARCHAR},
        </if>
        <if test="item.valid != null">
          n_valid = #{item.valid,jdbcType=INTEGER},
        </if>
        <if test="item.createTime != null">
          dt_create_time = #{item.createTime,jdbcType=TIMESTAMP},
        </if>
        <if test="item.updateTime != null">
          dt_update_time = #{item.updateTime,jdbcType=TIMESTAMP},
        </if>
        <if test="item.lastLoginTime != null">
          dt_last_login_time = #{item.lastLoginTime,jdbcType=TIMESTAMP}
        </if>
      </set>
      where n_id = #{item.id,jdbcType=BIGINT}
    </foreach>
  </update>
  <insert id="batchInsert" parameterType="java.util.List">
    insert into t_zlp_user (n_id, c_loginid, c_name, 
      c_password, c_phone, c_mail, 
      c_avatarurl, c_register_system, c_last_ip, 
      c_last_system, n_login_number, c_ext, 
      n_valid, dt_create_time, dt_update_time, 
      dt_last_login_time)
    values
    <foreach collection="list" item="item" separator=",">
      (#{item.id,jdbcType=BIGINT}, #{item.loginid,jdbcType=VARCHAR}, #{item.name,jdbcType=VARCHAR}, 
        #{item.password,jdbcType=VARCHAR}, #{item.phone,jdbcType=VARCHAR}, #{item.mail,jdbcType=VARCHAR}, 
        #{item.avatarurl,jdbcType=VARCHAR}, #{item.registerSystem,jdbcType=VARCHAR}, #{item.lastIp,jdbcType=VARCHAR}, 
        #{item.lastSystem,jdbcType=VARCHAR}, #{item.loginNumber,jdbcType=INTEGER}, #{item.ext,jdbcType=VARCHAR}, 
        #{item.valid,jdbcType=INTEGER}, #{item.createTime,jdbcType=TIMESTAMP}, #{item.updateTime,jdbcType=TIMESTAMP}, 
        #{item.lastLoginTime,jdbcType=TIMESTAMP})
    </foreach>
  </insert>
  <delete id="batchDelete">
    delete from t_zlp_user where n_id in
    <foreach close=")" collection="list" item="item" open="(" separator=",">
      #{item}
    </foreach>
  </delete>
  <select id="batchSelect" resultMap="BaseResultMap">
    select 
    <include refid="Base_Column_List" />
    from t_zlp_user
     where n_id in
    <foreach close=")" collection="list" item="item" open="(" separator=",">
      #{item}
    </foreach>
  </select>
  <delete id="deleteSelective">
    delete from t_zlp_user
    <include refid="BASE_QUERY" />
  </delete>
</mapper>